{"id":106,"university":{"fullName":"University of Chicago","shortName":"U Chicago","region":"North America","hashTag":"#UChicago","url":"www.cs.uchicago.edu","appearances":10,"wins":0,"gold":0,"silver":0,"bronze":0,"regionalChampionships":0},"team":{"name":"Sufficiently Advanced Tech","regionals":["The 2015 Mid-Central USA Regional Contest, 2nd","The 2015 University of Chicago Qualifying Contest, 1st"],"openCupPlace":-1,"openCupTimes":0},"coach":{"name":"Borja Sotomayor","altNames":[],"tcRating":-1,"cfRating":-1,"achievements":[{"achievement":"World Finals coach (2009-2016)","priority":1008}]},"contestants":[{"name":"Scott Shi","altNames":[],"tcRating":-1,"cfRating":-1,"achievements":[{"achievement":"ACM ICPC Finalist (2016)","priority":1001}]},{"name":"Mihai Andreescu","altNames":["Andreescu Mihai"],"tcRating":-1,"cfHandle":"mihai995","cfRating":1758,"achievements":[{"achievement":"ACM ICPC Finalist (2016)","priority":1001}]},{"name":"Nikolas Anderson","altNames":[],"tcRating":-1,"cfRating":-1,"achievements":[{"achievement":"ACM ICPC Finalist (2016)","priority":1001}]}]}