{"id":28,"university":{"fullName":"Indian Institute of Technology - Delhi","shortName":"IIT Delhi","region":"Asia","hashTag":"#IITDelhi","url":"www.iitd.ernet.in","appearances":4,"wins":0,"gold":0,"silver":0,"bronze":0,"regionalChampionships":0},"team":{"name":"angle","regionals":["The 2015 ACM-ICPC Asia Amritapuri Regional Contest, 1st","Asia Amritapuri First Round Online Programming Contest, 5th"],"openCupPlace":-1,"openCupTimes":0},"coach":{"name":"Mausam Mausam","altNames":[],"tcRating":-1,"cfRating":-1,"achievements":[]},"contestants":[{"name":"Kunal Singhal","altNames":[],"tcHandle":"knsn1994","tcId":"22917652","tcRating":1649,"cfHandle":"knsn","cfRating":1802,"achievements":[{"achievement":"ACM ICPC Finalist (2015)","priority":1001},{"achievement":"IOI Participant (2012)","priority":11}]},{"name":"Satwant Rana","altNames":["Rana Satwant"],"tcHandle":"satwant123","tcId":"23152984","tcRating":1564,"cfHandle":"TheTerminalGuy","cfRating":1898,"achievements":[{"achievement":"ACM ICPC Finalist (2015)","priority":1001}]},{"name":"Yash Kumar Bansal","altNames":["Yash Bansal","Bansal Yash"],"tcHandle":"yash_15","tcId":"40160692","tcRating":1267,"cfHandle":"yash_15","cfRating":1901,"achievements":[]}]}